README.rst
setup.py
intercity_tickets/__init__.py
intercity_tickets/notifications.py
intercity_tickets.egg-info/PKG-INFO
intercity_tickets.egg-info/SOURCES.txt
intercity_tickets.egg-info/dependency_links.txt
intercity_tickets.egg-info/entry_points.txt
intercity_tickets.egg-info/not-zip-safe
intercity_tickets.egg-info/requires.txt
intercity_tickets.egg-info/top_level.txt