Metadata-Version: 1.0
Name: intercity-tickets
Version: 0.0.1
Summary: It gets the details of your intercity tickets.
Home-page: https://github.com/bogdal/intercity-tickets
Author: Adam Bogdał
Author-email: adam@bogdal.pl
License: UNKNOWN
Platform: UNKNOWN
